AutomationServiceBackend/app/__init__.py
AutomationServiceBackend/app/endpoints.py
AutomationServiceBackend/app/format_input.py
AutomationServiceBackend/app/main.py
AutomationServiceBackend/app/qanarycomponent.py
AutomationServiceBackend/app/train_a_model.py
AutomationServiceBackend/app/helper/__init__.py
AutomationServiceBackend/app/helper/filehelper.py
AutomationServiceBackend/app/helper/generate_spacy_data.py
AutomationServiceBackend/app/helper/my_exceptions.py
AutomationServiceBackend/app/helper/spacy_trainer.py
AutomationServiceBackend/app/model/MLFlowLogging.py
AutomationServiceBackend/app/model/__init__.py
AutomationServiceBackend/app/model/request_handler.py
AutomationServiceBackend/app/spacy_model/__init__.py
AutomationServiceBackend/app/spacy_model/interact_with_spacy.py
AutomationServiceBackend/app/spacy_model/result_builder.py
AutomationServiceBackend/app/spacy_model/retrain_a_model.py
ExampleBodies/ExampleModels/address_nobase_en/__init__.py
ExampleBodies/ExampleModels/name_nobase_en/__init__.py
ExampleBodies/ExampleModels/spacy_address_model/__init__.py
ExampleBodies/ExampleModels/spacy_address_model/generate_spacy_data.py
ExampleBodies/ExampleModels/spacy_name_model/__init__.py
ExampleBodies/ExampleModels/spacy_name_model/generate_spacy_data.py
venv/lib/python3.11/site-packages/_distutils_hack/__init__.py
venv/lib/python3.11/site-packages/_distutils_hack/override.py
venv/lib/python3.11/site-packages/build/__init__.py
venv/lib/python3.11/site-packages/build/__main__.py
venv/lib/python3.11/site-packages/build/env.py
venv/lib/python3.11/site-packages/build/util.py
venv/lib/python3.11/site-packages/packaging/__init__.py
venv/lib/python3.11/site-packages/packaging/_elffile.py
venv/lib/python3.11/site-packages/packaging/_manylinux.py
venv/lib/python3.11/site-packages/packaging/_musllinux.py
venv/lib/python3.11/site-packages/packaging/_parser.py
venv/lib/python3.11/site-packages/packaging/_structures.py
qanary_ner_automl_component-1.0.2.dist-info/METADATA
qanary_ner_automl_component-1.0.2.dist-info/WHEEL
qanary_ner_automl_component-1.0.2.dist-info/licenses/LICENSE
qanary_ner_automl_component-1.0.2.dist-info/RECORD
