Metadata-Version: 2.1
Name: Qanary-NER-AutoML-component
Version: 1.0.2
Summary: A python project allowing to run a fastapi server that can train NER models and use them for identifying entities in runtime and can be included in a qanary environment if wished.
Project-URL: Homepage, https://github.com/WSE-research/Qanary-NER-automl-component
Project-URL: README, https://github.com/WSE-research/Qanary-NER-automl-component#readme
Project-URL: Bug Tracker, https://github.com/WSE-research/Qanary-NER-automl-component/issues
Author-email: Annemarie Wittig <wittiganmarie@gmail.com>
License-File: LICENSE
Classifier: License :: OSI Approved :: MIT License
Classifier: Operating System :: OS Independent
Classifier: Programming Language :: Python :: 3
Requires-Python: >=3.8
